asdcontroller/__init__.py
asdcontroller/asd_controller.py
asdcontroller/asd_types.py
asdcontroller-0.0.12.dist-info/METADATA
asdcontroller-0.0.12.dist-info/WHEEL
asdcontroller-0.0.12.dist-info/top_level.txt
asdcontroller-0.0.12.dist-info/RECORD
