Metadata-Version: 2.1
Name: asdcontroller
Version: 0.0.12
Summary: ASD Fieldspec 4 interface
Home-page: https://github.com/GOA-UVa/asdcontroller
Author: Group of Atmospheric Optics (GOA-UVa), Universidad de Valladolid
Author-email: gaton@goa.uva.es
Project-URL: Bug Tracker, https://github.com/GOA-UVa/asdcontroller/issues
Classifier: Programming Language :: Python :: 3
Classifier: Operating System :: OS Independent
Requires-Python: >=3.7
